lib_pipeline/__init__.py
lib_pipeline/docker.py
lib_pipeline/helpers.py
lib_pipeline/singleton.py
lib_pipeline/terraform.py
lib_pipeline/aws/__init__.py
lib_pipeline/aws/aws.py
lib_pipeline-0.0.12.dist-info/LICENSE
lib_pipeline-0.0.12.dist-info/METADATA
lib_pipeline-0.0.12.dist-info/WHEEL
lib_pipeline-0.0.12.dist-info/top_level.txt
lib_pipeline-0.0.12.dist-info/RECORD
