Metadata-Version: 2.1
Name: lib-pipeline
Version: 0.0.12
Summary: A python implementation of services to help deploy using aws and terraform
Home-page: https://github.com/balassit/lib_pipeline
Author: Blake Lassiter
Author-email: blakelass@gmail.com
License: UNKNOWN
Platform: UNKNOWN
Classifier: Programming Language :: Python :: 3
Classifier: License :: OSI Approved :: MIT License
Classifier: Operating System :: OS Independent
